gpu_free_ai-0.2.0.dist-info/METADATA
gpu_free_ai-0.2.0.dist-info/WHEEL
gpu_free_ai-0.2.0.dist-info/entry_points.txt
gpu_free_ai/__init__.py
gpu_free_ai/impl.py
gpu_free_ai/importer.py
gpu_free_ai-0.2.0.dist-info/RECORD
