Metadata-Version: 2.1
Name: gpu-free-ai
Version: 0.2.0
Summary: all the features of AI with 100% compute efficiency and no hardware requirements
Author-Email: sneakers-the-rat <sneakers-the-rat@protonmail.com>
License: MIT
Project-URL: repository, https://github.com/sneakers-the-rat/gpu-free-ai
Requires-Python: >=3.11
